{"type": "FeatureCollection", "features": [{"type": "Feature", "geometry": {"type": "Point", "coordinates": [8.49158908762024, 47.427090840119455]}, "properties": {"name": "Induction loops", "layer": "Induction loops"}}, {"type": "Feature", "geometry": {"type": "Point", "coordinates": [8.49158908762024, 47.427090840119455]}, "properties": {"name": "Induction loops", "layer": "Induction loops"}}, {"type": "Feature", "geometry": {"type": "Point", "coordinates": [8.565883695602711, 47.41595179886978]}, "properties": {"name": "Induction loops", "layer": "Induction loops"}}, {"type": "Feature", "geometry": {"type": "Point", "coordinates": [8.591016728021193, 47.40580431186599]}, "properties": {"name": "Induction loops", "layer": "Induction loops"}}, {"type": "Feature", "geometry": {"type": "Point", "coordinates": [8.493738027133348, 47.42583891955691]}, "properties": {"name": "Induction loops", "layer": "Induction loops"}}, {"type": "Feature", "geometry": {"type": "Point", "coordinates": [8.550125920255697, 47.430748153083336]}, "properties": {"name": "Induction loops", "layer": "Induction loops"}}, {"type": "Feature", "geometry": {"type": "Point", "coordinates": [8.550125920255697, 47.430748153083336]}, "properties": {"name": "Induction loops", "layer": "Induction loops"}}, {"type": "Feature", "geometry": {"type": "Point", "coordinates": [8.594868478874208, 47.3970855081348]}, "properties": {"name": "Induction loops", "layer": "Induction loops"}}, {"type": "Feature", "geometry": {"type": "Point", "coordinates": [8.492650413510972, 47.42646950677365]}, "properties": {"name": "Induction loops", "layer": "Induction loops"}}, {"type": "Feature", "geometry": {"type": "Point", "coordinates": [8.493738027133348, 47.42583891955691]}, "properties": {"name": "Induction loops", "layer": "Induction loops"}}, {"type": "Feature", "geometry": {"type": "Point", "coordinates": [8.591016728021193, 47.40580431186599]}, "properties": {"name": "Induction loops", "layer": "Induction loops"}}, {"type": "Feature", "geometry": {"type": "Point", "coordinates": [8.59501967481656, 47.40465793198369]}, "properties": {"name": "Induction loops", "layer": "Induction loops"}}, {"type": "Feature", "geometry": {"type": "Point", "coordinates": [8.565883695602711, 47.41595179886978]}, "properties": {"name": "Induction loops", "layer": "Induction loops"}}, {"type": "Feature", "geometry": {"type": "Point", "coordinates": [8.492650413510972, 47.42646950677365]}, "properties": {"name": "Induction loops", "layer": "Induction loops"}}, {"type": "Feature", "geometry": {"type": "Point", "coordinates": [8.594868478874208, 47.3970855081348]}, "properties": {"name": "Induction loops", "layer": "Induction loops"}}, {"type": "Feature", "geometry": {"type": "Point", "coordinates": [8.59501967481656, 47.40465793198369]}, "properties": {"name": "Induction loops", "layer": "Induction loops"}}]}